kroget/__init__.py
kroget/cli.py
kroget/tui.py
kroget/core/__init__.py
kroget/core/paths.py
kroget/core/product_display.py
kroget/core/product_upc.py
kroget/core/proposal.py
kroget/core/proposal_merge.py
kroget/core/recent_searches.py
kroget/core/sent_items.py
kroget/core/staple_name.py
kroget/core/storage.py
kroget/kroger/__init__.py
kroget/kroger/auth.py
kroget/kroger/client.py
kroget/kroger/models.py
kroget-0.4.0.dist-info/licenses/LICENSE
kroget-0.4.0.dist-info/METADATA
kroget-0.4.0.dist-info/WHEEL
kroget-0.4.0.dist-info/entry_points.txt
kroget-0.4.0.dist-info/top_level.txt
kroget-0.4.0.dist-info/RECORD
