Metadata-Version: 2.4
Name: kroget
Version: 0.4.0
Summary: Kroger shopping CLI
Author: Kroget Contributors
License: MIT
Keywords: kroger,cli
Classifier: Programming Language :: Python :: 3
Classifier: Programming Language :: Python :: 3.12
Requires-Python: >=3.12
License-File: LICENSE
Requires-Dist: typer[all]
Requires-Dist: rich
Requires-Dist: httpx
Requires-Dist: pydantic>=2
Requires-Dist: python-dotenv
Requires-Dist: textual
Provides-Extra: dev
Requires-Dist: build; extra == "dev"
Requires-Dist: commitizen; extra == "dev"
Requires-Dist: pytest; extra == "dev"
Requires-Dist: pytest-asyncio; extra == "dev"
Requires-Dist: ruff; extra == "dev"
Dynamic: license-file
